example/__init__.py
example/config.py
example/models.py
example/simple_blog.py
flask_modular_auth/__init__.py
flask_modular_auth/abstract.py
flask_modular_auth/auth_providers.py
flask_modular_auth/manager.py
flask_modular_auth/privilege.py
flask_modular_auth/utils.py
flask_modular_auth-0.2.dist-info/DESCRIPTION.rst
flask_modular_auth-0.2.dist-info/METADATA
flask_modular_auth-0.2.dist-info/RECORD
flask_modular_auth-0.2.dist-info/WHEEL
flask_modular_auth-0.2.dist-info/metadata.json
flask_modular_auth-0.2.dist-info/top_level.txt
tests/__init__.py
tests/modular_auth_test_case.py
tests/test_auth_provider_registration.py
tests/test_auth_providers.py
