Metadata-Version: 2.0
Name: flask-modular-auth
Version: 0.2
Summary: UNKNOWN
Home-page: UNKNOWN
Author: UNKNOWN
Author-email: UNKNOWN
License: UNKNOWN
Platform: UNKNOWN
Requires-Dist: flask
